pytmpinv-1.6.0.dist-info/licenses/LICENSE
tmpinv/__init__.py
tmpinv/tmpinv.py
pytmpinv-1.6.0.dist-info/METADATA
pytmpinv-1.6.0.dist-info/WHEEL
pytmpinv-1.6.0.dist-info/top_level.txt
pytmpinv-1.6.0.dist-info/RECORD
